__init__.py
setup.py
stopwatch/__init__.py
timemanager-1.0.3.dist-info/METADATA
timemanager-1.0.3.dist-info/WHEEL
timemanager-1.0.3.dist-info/RECORD
