Metadata-Version: 2.1
Name: TimeManager
Version: 1.0.3
Summary: A python module which helps you manage time related tasks.
